aristoteDash/__init__.py
aristoteDash/aristote.py
aristoteDash/aristoteDash.py
aristoteDash/confFiles/aristote.md
aristotePV-1.5.dist-info/METADATA
aristotePV-1.5.dist-info/WHEEL
aristotePV-1.5.dist-info/top_level.txt
aristotePV-1.5.dist-info/RECORD
