Metadata-Version: 2.1
Name: aristotePV
Version: 1.5
Summary: Programme de prévision de production électrique d'une centrale PV
Home-page: UNKNOWN
Author: Dorian Drevon
Author-email: drevondorian@gmail.com
License: UNKNOWN
Platform: UNKNOWN
Classifier: Programming Language :: Python :: 3
Classifier: License :: OSI Approved :: MIT License
Classifier: Operating System :: OS Independent
Requires-Python: >=3.8
Requires-Dist: dorianUtils (==5.1.2)
Requires-Dist: geopy (==2.2.0)
Requires-Dist: tzwhere (==3.0.3)
